DarkMute-0.1.8.dist-info/METADATA
DarkMute-0.1.8.dist-info/RECORD
DarkMute-0.1.8.dist-info/WHEEL
DarkMute-0.1.8.dist-info/entry_points.txt
DarkMute-0.1.8.dist-info/top_level.txt
darkmute/__init__.py
darkmute/__main__.py
darkmute/dark_mute.py
darkmute/snap.py
