Metadata-Version: 2.1
Name: DarkMute
Version: 0.1.8
Summary: Mute snapcast client playing on raspi3
Home-page: https://git.xhost.io/jess/Dark-Mute
Author: Jessica Ward
License: UNKNOWN
Platform: UNKNOWN
Classifier: License :: OSI Approved :: MIT License
Classifier: Intended Audience :: System Administrators
Classifier: Intended Audience :: Developers
Classifier: Programming Language :: Python :: 3
Classifier: Topic :: System :: Hardware
Requires-Dist: RPi.GPIO (==0.6.3)
Requires-Dist: snapcast (==2.0.8)
Requires-Dist: zeroconf (==0.20.0)
